LICENSE
MANIFEST.in
README.md
pyproject.toml
setup.py
libcint/AUTHORS
libcint/CMakeLists.txt
libcint/ChangeLog
libcint/LICENSE
libcint/README.rst
libcint/cmake/FindQUADMATH.cmake
libcint/doc/compile.sh
libcint/doc/libcint.CPack.txt
libcint/doc/program_ref.tex
libcint/doc/program_ref.txt
libcint/include/cint.h.in
libcint/include/cint_funcs.h
libcint/src/breit.c
libcint/src/c2f.c
libcint/src/c2f.h
libcint/src/cart2sph.c
libcint/src/cart2sph.h
libcint/src/cint1e.c
libcint/src/cint1e.h
libcint/src/cint1e_a.c
libcint/src/cint1e_grids.c
libcint/src/cint2c2e.c
libcint/src/cint2e.c
libcint/src/cint2e.h
libcint/src/cint2e_f12.c
libcint/src/cint3c1e.c
libcint/src/cint3c1e_a.c
libcint/src/cint3c2e.c
libcint/src/cint4c1e.c
libcint/src/cint_bas.c
libcint/src/cint_bas.h
libcint/src/cint_config.h.in
libcint/src/eigh.c
libcint/src/fblas.c
libcint/src/fblas.h
libcint/src/find_roots.c
libcint/src/fmt.c
libcint/src/g1e.c
libcint/src/g1e.h
libcint/src/g1e_grids.c
libcint/src/g1e_grids.h
libcint/src/g2c2e.c
libcint/src/g2e.c
libcint/src/g2e.h
libcint/src/g2e_f12.c
libcint/src/g3c1e.c
libcint/src/g3c1e.h
libcint/src/g3c2e.c
libcint/src/g4c1e.c
libcint/src/gout2e_simd.c
libcint/src/misc.c
libcint/src/misc.h
libcint/src/optimizer.c
libcint/src/optimizer.h
libcint/src/polyfits.c
libcint/src/roots_for_x0.dat
libcint/src/roots_xw.dat
libcint/src/rys_roots.c
libcint/src/rys_roots.h
libcint/src/rys_wheeler.c
libcint/src/sr_roots_part0_w.dat
libcint/src/sr_roots_part0_x.dat
libcint/src/sr_roots_part1_w.dat
libcint/src/sr_roots_part1_x.dat
libcint/src/sr_roots_part2_w.dat
libcint/src/sr_roots_part2_x.dat
libcint/src/sr_roots_part3_w.dat
libcint/src/sr_roots_part3_x.dat
libcint/src/sr_rys_polyfits.c
libcint/src/stg_roots.c
libcint/src/autocode/breit1.c
libcint/src/autocode/deriv3.c
libcint/src/autocode/deriv4.c
libcint/src/autocode/dkb.c
libcint/src/autocode/gaunt1.c
libcint/src/autocode/grad1.c
libcint/src/autocode/grad2.c
libcint/src/autocode/hess.c
libcint/src/autocode/int1e_grids1.c
pycint.egg-info/PKG-INFO
pycint.egg-info/SOURCES.txt
pycint.egg-info/dependency_links.txt
pycint.egg-info/requires.txt
pycint.egg-info/top_level.txt