Metadata-Version: 2.4
Name: pycint
Version: 6.1.3.5
Summary: Python wrapper for libcint.
Author-email: Ihe Fan <ih.fan.1027@gmail.com>
License-Expression: Apache-2.0
Classifier: Programming Language :: Python :: 3
Classifier: Programming Language :: Python :: 3 :: Only
Requires-Python: >=3.12
License-File: LICENSE
Requires-Dist: numpy
Requires-Dist: cffi>=2
Dynamic: license-file
